cli_tools/__init__.py
cli_tools/__init__.pyi
cli_tools/_ansi_support.py
cli_tools/_api_builder.py
cli_tools/cli.py
cli_tools/exceptions.py
cli_tools/patterns.py
cli_tools/styles.py
cli_tools/terminal.py
cli_tools/utils.py
cli_tools/validators.py
cli_tools_by_oleksa-2.2.0.dist-info/METADATA
cli_tools_by_oleksa-2.2.0.dist-info/WHEEL
cli_tools_by_oleksa-2.2.0.dist-info/licenses/LICENSE
cli_tools_by_oleksa-2.2.0.dist-info/RECORD
