Metadata-Version: 2.4
Name: cli_tools_by_oleksa
Version: 2.2.0
Summary: Lightweight helper toolkit for building CLI (command-line) applications in Python.
Author: Oleksa
License-Expression: MIT
License-File: LICENSE
Keywords: ansi,cli,composition,console,cursor-control,error-handling,input-validation,interactive,menu,menu-selection,no-dependency,prompt,regex,rgb,styling,table,terminal,true-color,validators
Classifier: Development Status :: 5 - Production/Stable
Classifier: Environment :: Console
Classifier: Intended Audience :: Developers
Classifier: Intended Audience :: Education
Classifier: License :: OSI Approved :: MIT License
Classifier: Operating System :: OS Independent
Classifier: Programming Language :: Python :: 3
Classifier: Programming Language :: Python :: 3.10
Classifier: Programming Language :: Python :: 3.11
Classifier: Programming Language :: Python :: 3.12
Classifier: Programming Language :: Python :: 3.13
Classifier: Programming Language :: Python :: 3.14
Classifier: Topic :: Education
Classifier: Topic :: Software Development
Classifier: Topic :: Software Development :: Libraries :: Python Modules
Classifier: Topic :: Software Development :: User Interfaces
Classifier: Topic :: Terminals
Classifier: Topic :: Utilities
Requires-Python: >=3.10
